.hgignore
.installed.cfg
.project
.pydevproject
LICENSE
MANIFEST.in
README.txt
bootstrap.py
buildout.cfg
setup.py
bin/buildout
docs/HISTORY.txt
docs/README.txt
src/ztfy/__init__.py
src/ztfy.jqueryui.egg-info/PKG-INFO
src/ztfy.jqueryui.egg-info/SOURCES.txt
src/ztfy.jqueryui.egg-info/dependency_links.txt
src/ztfy.jqueryui.egg-info/entry_points.txt
src/ztfy.jqueryui.egg-info/namespace_packages.txt
src/ztfy.jqueryui.egg-info/not-zip-safe
src/ztfy.jqueryui.egg-info/requires.txt
src/ztfy.jqueryui.egg-info/top_level.txt
src/ztfy/jqueryui/README.txt
src/ztfy/jqueryui/__init__.py
src/ztfy/jqueryui/doctests/README.txt
src/ztfy/jqueryui/locales/ztfy.jqueryui.pot
src/ztfy/jqueryui/resources/css/jquery-alerts.css
src/ztfy/jqueryui/resources/css/jquery-alerts.min.css
src/ztfy/jqueryui/resources/css/jquery-colorpicker.css
src/ztfy/jqueryui/resources/css/jquery-colorpicker.min.css
src/ztfy/jqueryui/resources/css/jquery-datatables.css
src/ztfy/jqueryui/resources/css/jquery-datatables.min.css
src/ztfy/jqueryui/resources/css/jquery-datetime.css
src/ztfy/jqueryui/resources/css/jquery-datetime.min.css
src/ztfy/jqueryui/resources/css/jquery-fancybox-1.3.4.css
src/ztfy/jqueryui/resources/css/jquery-fancybox-1.3.4.min.css
src/ztfy/jqueryui/resources/css/jquery-fancybox.min.css
src/ztfy/jqueryui/resources/css/jquery-handsontable-full.css
src/ztfy/jqueryui/resources/css/jquery-handsontable-full.min.css
src/ztfy/jqueryui/resources/css/jquery-imgareaselect.css
src/ztfy/jqueryui/resources/css/jquery-imgareaselect.min.css
src/ztfy/jqueryui/resources/css/jquery-jscrollpane.css
src/ztfy/jqueryui/resources/css/jquery-jscrollpane.min.css
src/ztfy/jqueryui/resources/css/jquery-jtip.css
src/ztfy/jqueryui/resources/css/jquery-jtip.min.css
src/ztfy/jqueryui/resources/css/jquery-layout.css
src/ztfy/jqueryui/resources/css/jquery-layout.min.css
src/ztfy/jqueryui/resources/css/jquery-liquidcarousel.css
src/ztfy/jqueryui/resources/css/jquery-liquidcarousel.min.css
src/ztfy/jqueryui/resources/css/jquery-multiselect.css
src/ztfy/jqueryui/resources/css/jquery-multiselect.min.css
src/ztfy/jqueryui/resources/css/jquery-tipsy.css
src/ztfy/jqueryui/resources/css/jquery-tipsy.min.css
src/ztfy/jqueryui/resources/css/jquery-treeTable.css
src/ztfy/jqueryui/resources/css/jquery-treeTable.min.css
src/ztfy/jqueryui/resources/css/jquery-ui-1.7.3.css
