Metadata-Version: 1.1
Name: ztfy.jqueryui
Version: 0.7.12
Summary: A package containing JQuery, JQuery UI, JQuery Tools and a small set of JQuery plugins
Home-page: http://www.ztfy.org
Author: Thierry Florac
Author-email: tflorac@ulthar.net
License: ZPL
Keywords: ZTFY JQuery UI package
Platform: UNKNOWN
Classifier: License :: OSI Approved :: Zope Public License
Classifier: Development Status :: 4 - Beta
Classifier: Programming Language :: Python
Classifier: Framework :: Zope3
Classifier: Topic :: Software Development :: Libraries :: Python Modules
